lineagetree/__init__.py
lineagetree/lineage_tree.py
lineagetree/lineage_tree_manager.py
lineagetree/plot.py
lineagetree/tree_approximation.py
lineagetree/_core/_modifier.py
lineagetree/_core/_navigation.py
lineagetree/_core/_properties.py
lineagetree/_core/utils.py
lineagetree/_core/validation.py
lineagetree/_io/_loaders.py
lineagetree/_io/_writers.py
lineagetree/_legacy/export_csv.py
lineagetree/_legacy/to_lineajea.py
lineagetree/_legacy/to_motile.py
lineagetree/_mixins/_methodize.py
lineagetree/_mixins/analysis_mixin.py
lineagetree/_mixins/io_mixin.py
lineagetree/_mixins/modifier_mixin.py
lineagetree/_mixins/navigation_mixin.py
lineagetree/_mixins/plot_mixin.py
lineagetree/_mixins/properties_mixin.py
lineagetree/_mixins/spatial_mixin.py
lineagetree/approximation/delta_functions.py
lineagetree/measure/dynamic_time_warping.py
lineagetree/measure/spatial.py
lineagetree/measure/uted.py
lineagetree-3.0.4.dist-info/licenses/LICENSE
lineagetree-3.0.4.dist-info/METADATA
lineagetree-3.0.4.dist-info/WHEEL
lineagetree-3.0.4.dist-info/top_level.txt
lineagetree-3.0.4.dist-info/RECORD
