Metadata-Version: 2.4
Name: lineagetree
Version: 3.0.4
Summary: Structure for Lineage Trees
Author: Giannis Liaskas, Christopher Mazzerbo
Author-email: Léo Guignard <leo.guignard@univ-amu.fr>
Maintainer-email: Léo Guignard <leo.guignard@univ-amu.fr>
License-Expression: MIT
Project-URL: Bug Tracker, https://github.com/GuignardLab/LineageTree/issues
Project-URL: Documentation, https://github.com/GuignardLab/LineageTree#README.md
Project-URL: Source Code, https://github.com/GuignardLab/LineageTree
Project-URL: User Support, https://github.com/GuignardLab/LineageTree/issues
Classifier: Development Status :: 4 - Beta
Classifier: Intended Audience :: Developers
Classifier: Operating System :: OS Independent
Classifier: Programming Language :: Python
Classifier: Programming Language :: Python :: 3
Classifier: Programming Language :: Python :: 3 :: Only
Classifier: Programming Language :: Python :: 3.10
Classifier: Programming Language :: Python :: 3.11
Classifier: Programming Language :: Python :: 3.12
Classifier: Programming Language :: Python :: 3.13
Requires-Python: >=3.10
License-File: LICENSE
Requires-Dist: scipy>=1.9
Requires-Dist: numpy>=1.23
Requires-Dist: matplotlib
Requires-Dist: edist
Requires-Dist: svgwrite
Requires-Dist: Micro-Mastodon-Reader
Requires-Dist: binarymeshformat
Provides-Extra: dev
Requires-Dist: pytest; extra == "dev"
Requires-Dist: pytest-cov; extra == "dev"
Requires-Dist: black; extra == "dev"
Requires-Dist: ruff; extra == "dev"
Requires-Dist: bumpver; extra == "dev"
Provides-Extra: doc
Requires-Dist: sphinx-rtd-theme; extra == "doc"
Requires-Dist: myst-parser; extra == "doc"
Requires-Dist: sphinx_book_theme; extra == "doc"
Provides-Extra: test
Requires-Dist: pytest; extra == "test"
Requires-Dist: pytest-cov; extra == "test"
Dynamic: license-file
